MANIFEST.in
README.rst
requirements.txt
setup.py
docs/Makefile
docs/make.bat
docs/source/index.rst
javascript/webapi/cache.js
javascript/webapi/client.js
javascript/webapi/httprequest.js
javascript/webapi/loader.js
javascript/webapi/loader_test.js
javascript/webapi/rpcrequest.js
javascript/webapi/rpcrequest_test.js
javascript/webapi/discovery/directoryitem.js
javascript/webapi/discovery/directorylist.js
javascript/webapi/discovery/restdescription.js
javascript/webapi/discovery/restdescription_test.js
javascript/webapi/discovery/restmethod.js
python/webapi/__init__.py
python/webapi/apidescription.py
python/webapi/client.py
python/webapi/decorators.py
python/webapi/directoryhandler.py
python/webapi/discovery.py
python/webapi/errors.py
python/webapi/handler.py
python/webapi/handler_test.py
python/webapi/protojson.py
python/webapi/service.py
webapi.egg-info/PKG-INFO
webapi.egg-info/SOURCES.txt
webapi.egg-info/dependency_links.txt
webapi.egg-info/top_level.txt