Metadata-Version: 1.1
Name: webapi
Version: 0.1
Summary: A framework to build web (json-rpc) APIs.
Home-page: https://code.google.com/p/webapi
Author: nate skulic
Author-email: nate.skulic@gmail.com
License: UNKNOWN
Platform: UNKNOWN
Requires: protorpc
